LICENSE
MANIFEST.in
README.md
pyproject.toml
setup.cfg
setup.py
tap_zendesk_chat/__init__.py
tap_zendesk_chat/context.py
tap_zendesk_chat/discover.py
tap_zendesk_chat/http.py
tap_zendesk_chat/streams.py
tap_zendesk_chat/sync.py
tap_zendesk_chat/utils.py
tap_zendesk_chat.egg-info/PKG-INFO
tap_zendesk_chat.egg-info/SOURCES.txt
tap_zendesk_chat.egg-info/dependency_links.txt
tap_zendesk_chat.egg-info/entry_points.txt
tap_zendesk_chat.egg-info/requires.txt
tap_zendesk_chat.egg-info/top_level.txt
tap_zendesk_chat/schemas/account.json
tap_zendesk_chat/schemas/agents.json
tap_zendesk_chat/schemas/bans.json
tap_zendesk_chat/schemas/chat_conversion.json
tap_zendesk_chat/schemas/chat_count.json
tap_zendesk_chat/schemas/chat_history.json
tap_zendesk_chat/schemas/chat_response_time.json
tap_zendesk_chat/schemas/chat_visitor.json
tap_zendesk_chat/schemas/chat_webpath.json
tap_zendesk_chat/schemas/chats.json
tap_zendesk_chat/schemas/departments.json
tap_zendesk_chat/schemas/goals.json
tap_zendesk_chat/schemas/shortcuts.json
tap_zendesk_chat/schemas/triggers.json