Metadata-Version: 2.1
Name: tap-zendesk-chat
Version: 0.4.0
Summary: Singer.io tap for extracting data from the Zendesk Chat API
Home-page: https://singer.io
Author: Stitch
License: UNKNOWN
Platform: UNKNOWN
Classifier: Programming Language :: Python :: 3 :: Only
Provides-Extra: dev
